pygame_framework/pygame_framework.py
pygame_framework-0.0.1.dist-info/METADATA
pygame_framework-0.0.1.dist-info/WHEEL
pygame_framework-0.0.1.dist-info/top_level.txt
pygame_framework-0.0.1.dist-info/RECORD
