Metadata-Version: 2.1
Name: pygame-framework
Version: 0.0.1
Summary: something for my project
Home-page: https://github.com/PetrKorab/Animated-Word-Cloud-in-Economics
Author: Petr Koráb
Author-email: Petr Korab <xpetrkorab@gmail.com>
Project-URL: Homepage, https://github.com/PetrKorab/Animated-Word-Cloud-in-Economics
Project-URL: Bug Tracker, https://github.com/PetrKorab/Animated-Word-Cloud-in-Economics/issues
Classifier: Programming Language :: Python :: 3.8
Classifier: License :: OSI Approved :: Apache Software License
Classifier: Operating System :: OS Independent
Requires-Python: >=3.8, <3.9
